ENSEK-1.8.0.dist-info/METADATA
ENSEK-1.8.0.dist-info/RECORD
ENSEK-1.8.0.dist-info/WHEEL
ENSEK-1.8.0.dist-info/top_level.txt
ensek/__init__.py
ensek/client.py
