Metadata-Version: 2.1
Name: ENSEK
Version: 1.8.0
Summary: Python Client for the ENSEK API (http://www.ensek.co.uk/) 
Home-page: https://github.com/Usio-Energy/ENSEK
Author: Richard O'Dwyer
Author-email: richard@richard.do
License: Apache 2
Platform: UNKNOWN
Classifier: License :: OSI Approved :: Apache Software License
Classifier: Programming Language :: Python
Classifier: Programming Language :: Python :: 3
Classifier: Programming Language :: Python :: 3.6
Classifier: Programming Language :: Python :: Implementation :: CPython
Classifier: Programming Language :: Python :: Implementation :: PyPy
Requires-Python: >=3.6.0
Requires-Dist: requests (>=0.10)
Requires-Dist: wheel (>=0.30.0)
Requires-Dist: setuptools (>=39.0.1)
Requires-Dist: stringcase (==1.2.0)
Requires-Dist: tenacity (==5.0.2)
